{
  "orders": [
    {
      "items": [
        {
          "productId": 1,
          "productName": "The Hobbit",
          "quantity": 2,
          "price": 32.4
        },
        {
          "productId": 2,
          "productName": "Martin Iden",
          "quantity": 3,
          "price": 25.5
        }
      ],
      "shippingAddress": "test",
      "customerId": "a1s2d2",
      "cost": 141.3,
      "id": 1
    },
    {
      "items": [
        {
          "productId": 1,
          "productName": "The Hobbit",
          "quantity": 1,
          "price": 32.4
        }
      ],
      "shippingAddress": "test",
      "customerId": "a1s2d2",
      "cost": 32.4,
      "id": 2
    },
    {
      "items": [
        {
          "productId": 2,
          "productName": "Martin Iden",
          "quantity": 5,
          "price": 25.5
        }
      ],
      "customerId": "a1s2d2",
      "cost": 127.5,
      "id": 4
    },
    {
      "items": [
        {
          "productId": 1,
          "productName": "The Hobbit",
          "quantity": 3,
          "price": 32.4
        }
      ],
      "customerId": "a1a1a1",
      "cost": 97.2,
      "id": 5
    },
    {
      "items": [
        {
          "productId": 2,
          "productName": "Martin Iden",
          "quantity": 3,
          "price": 25.5
        }
      ],
      "customerId": "a1a1a1",
      "cost": 76.5,
      "id": 6
    },
    {
      "items": [
        {
          "productId": 1,
          "productName": "The Hobbit",
          "quantity": 1,
          "price": 32.4
        }
      ],
      "customerId": "a1a1a1",
      "cost": 32.4,
      "id": 7
    }
  ],
  "users": [
    {
      "id": "a1s2d2",
      "firstName": "Anna",
      "lastName": "Borisova",
      "login": "anna",
      "password": "1234"
    },
    {
      "id": "a1a1a1",
      "firstName": "Ivan",
      "lastName": "Ivanov",
      "login": "admin",
      "password": "1234"
    }
  ],
  "books": [
    {
      "id": 1,
      "name": "The Hobbit",
      "description": "Adventures of Bilbo Baggins",
      "price": 32.4,
      "author": "J.R.R.Tolkien",
      "genre": "Fantasy"
    },
    {
      "id": 2,
      "name": "Martin Iden",
      "description": "One of Jack London's greatest works",
      "price": 25.5,
      "author": "J.London",
      "genre": "Künstlerroman"
    }
  ]
}